br_posts/__init__.py
br_posts/errors.py
br_posts/fare.py
br_posts/options.py
pyBRPost-1.0.1.dist-info/LICENSE
pyBRPost-1.0.1.dist-info/METADATA
pyBRPost-1.0.1.dist-info/WHEEL
pyBRPost-1.0.1.dist-info/top_level.txt
pyBRPost-1.0.1.dist-info/RECORD
