Metadata-Version: 2.1
Name: pyBRPost
Version: 1.0.1
Summary: Python module to query Brazilian Post Office regarding shipping methods
Home-page: https://github.com/minterciso/pyBRPost
Author: Mateus Interciso
Author-email: minterciso@gmail.com
License: MIT License
Platform: UNKNOWN
Classifier: Programming Language :: Python :: 3
Classifier: License :: OSI Approved :: MIT License
Classifier: Operating System :: OS Independent
Requires-Dist: requests (>=2.21.0)
Requires-Dist: xmltodict (>=0.12)
